pycountry_wrapper/__init__.py
pycountry_wrapper/__main__.py
pycountry_wrapper/config.py
pycountry_wrapper/country.py
pycountry_wrapper-1.0.1.dist-info/METADATA
pycountry_wrapper-1.0.1.dist-info/WHEEL
pycountry_wrapper-1.0.1.dist-info/entry_points.txt
pycountry_wrapper-1.0.1.dist-info/licenses/LICENSE
pycountry_wrapper-1.0.1.dist-info/RECORD
