Metadata-Version: 2.4
Name: pycountry-wrapper
Version: 1.0.1
Summary: This is a wrapper for pycountry, to make said library more usable.
Project-URL: Homepage, https://github.com/hazel-noack/pycountry-wrapper
Project-URL: Issues, https://github.com/hazel-noack/pycountry-wrapper/issues
Author-email: Hazel Noack <hazel@webcontact.de>
License-File: LICENSE
Classifier: License :: OSI Approved :: MIT License
Classifier: Operating System :: OS Independent
Classifier: Programming Language :: Python :: 3
Requires-Python: >=3.8
Requires-Dist: pycountry~=24.6.1
